vp4jl/__init__.py
vp4jl/_version.py
vp4jl/handlers.py
vp4jl/tests/__init__.py
vp4jl/tests/test_handlers.py
vp4jl-0.1.9.data/data/etc/jupyter/jupyter_notebook_config.d/vp4jl.json
vp4jl-0.1.9.data/data/etc/jupyter/jupyter_server_config.d/vp4jl.json
vp4jl-0.1.9.data/data/share/jupyter/labextensions/vp4jl/package.json
vp4jl-0.1.9.data/data/share/jupyter/labextensions/vp4jl/static/155.7f405a8095cea8450e9e.js
vp4jl-0.1.9.data/data/share/jupyter/labextensions/vp4jl/static/295.323f758d6846d2c1aaf0.js
vp4jl-0.1.9.data/data/share/jupyter/labextensions/vp4jl/static/539.19e1cb8a21cc3ac6eafc.js
vp4jl-0.1.9.data/data/share/jupyter/labextensions/vp4jl/static/582.51bd808859600bd28d28.js
vp4jl-0.1.9.data/data/share/jupyter/labextensions/vp4jl/static/586.9763ccb8d2e341ead176.js
vp4jl-0.1.9.data/data/share/jupyter/labextensions/vp4jl/static/681.b15ee6f078aef30e3852.js
vp4jl-0.1.9.data/data/share/jupyter/labextensions/vp4jl/static/730.76e65af579515379be7a.js
vp4jl-0.1.9.data/data/share/jupyter/labextensions/vp4jl/static/730.76e65af579515379be7a.js.LICENSE.txt
vp4jl-0.1.9.data/data/share/jupyter/labextensions/vp4jl/static/747.5f00b4009d5740253210.js
vp4jl-0.1.9.data/data/share/jupyter/labextensions/vp4jl/static/86.aba30179e86367171d7c.js
vp4jl-0.1.9.data/data/share/jupyter/labextensions/vp4jl/static/remoteEntry.9b055ea4af4efad6d876.js
vp4jl-0.1.9.data/data/share/jupyter/labextensions/vp4jl/static/style.js
vp4jl-0.1.9.data/data/share/jupyter/labextensions/vp4jl/static/third-party-licenses.json
vp4jl-0.1.9.data/data/share/jupyter/labextensions/vp4jl/install.json
vp4jl-0.1.9.dist-info/METADATA
vp4jl-0.1.9.dist-info/WHEEL
vp4jl-0.1.9.dist-info/licenses/LICENSE
vp4jl-0.1.9.dist-info/RECORD
